pyfinderbliss/__init__.py
pyfinderbliss/__main__.py
pyfinderbliss/api.py
pyfinderbliss/auth.py
pyfinderbliss/connection.py
pyfinderbliss/const.py
pyfinderbliss/device_parser.py
pyfinderbliss/websocket_handler.py
pyFinderBliss-0.1.5a0.dist-info/LICENSE
pyFinderBliss-0.1.5a0.dist-info/METADATA
pyFinderBliss-0.1.5a0.dist-info/WHEEL
pyFinderBliss-0.1.5a0.dist-info/top_level.txt
pyFinderBliss-0.1.5a0.dist-info/RECORD
