Metadata-Version: 2.1
Name: pyFinderBliss
Version: 0.1.5a0
Summary: A library to interact with FINDER BLISS thermostats
Home-page: https://github.com/condatek/pyFinderBliss
Author: Oliver Lee Chachou
Author-email: olli90.ita@gmail.com
License: MIT
Classifier: Programming Language :: Python :: 3
Classifier: License :: OSI Approved :: MIT License
Classifier: Operating System :: OS Independent
Requires-Python: >=3.6
License-File: LICENSE
